painface_lc-0.1.4.data/scripts/painface
painface_lc-0.1.4.data/scripts/painface.bat
painface_lc-0.1.4.data/scripts/painface.py
painface_lc-0.1.4.dist-info/licenses/LICENSE
painfacelib/__init__.py
painfacelib/config.py
painfacelib/cli/__init__.py
painfacelib/common/__init__.py
painfacelib/common/dataset.py
painfacelib/common/module.py
painfacelib/common/utils.py
painfacelib/common/video.py
painfacelib/common/visualize.py
painfacelib/data/__init__.py
painfacelib/data/application_data.json
painfacelib/ml/__init__.py
painfacelib/ml/estimate.py
painfacelib/ui/__init__.py
painfacelib/ui/gui.py
painfacelib/ui/tui.py
painfacelib/ui/tui.tcss
painfacelib/ui/glib/__init__.py
painfacelib/ui/glib/videoloading.py
painface_lc-0.1.4.dist-info/METADATA
painface_lc-0.1.4.dist-info/WHEEL
painface_lc-0.1.4.dist-info/top_level.txt
painface_lc-0.1.4.dist-info/RECORD
